watchdog_host/__init__.py
watchdog_host/bandwidth.py
watchdog_host/cli.py
watchdog_host/config.yaml
watchdog_host/notifier.py
watchdog_host/smartmon.py
watchdog_host/systemd/watchdog-bandwidth.service
watchdog_host/systemd/watchdog-smartmon.service
watchdog_host-1.0.3.dist-info/METADATA
watchdog_host-1.0.3.dist-info/WHEEL
watchdog_host-1.0.3.dist-info/entry_points.txt
watchdog_host-1.0.3.dist-info/RECORD
