Metadata-Version: 2.4
Name: watchdog-host
Version: 1.0.3
Summary: Watchdog Host is a tool for automatically managing hosts.
Author-email: John <me@hakr.xyz>
License: MIT
Requires-Python: >=3.10
Requires-Dist: psutil>=7.2.1
Requires-Dist: pysmart>=1.4.2
Requires-Dist: pyyaml>=6.0.3
Requires-Dist: requests>=2.32.5
Requires-Dist: typer>=0.21.0
